zephyros1938/tsapp.py
zephyros1938/tsappMod.py
tsappwrapper_zephyros1938-0.0.5.dist-info/LICENSE
tsappwrapper_zephyros1938-0.0.5.dist-info/METADATA
tsappwrapper_zephyros1938-0.0.5.dist-info/WHEEL
tsappwrapper_zephyros1938-0.0.5.dist-info/top_level.txt
tsappwrapper_zephyros1938-0.0.5.dist-info/RECORD
