Metadata-Version: 2.2
Name: tsappWrapper-zephyros1938
Version: 0.0.5
Summary: A package that modifies Techsmart's Tsapp
Author-email: Author <zephyros@zephyros1938.org>
Project-URL: Homepage, https://github.com/zephyros1938/tsapp_wrapper
Project-URL: Issues, https://github.com/zephyros1938/tsapp_wrapper/issues
Classifier: Programming Language :: Python :: 3
Classifier: Operating System :: OS Independent
Classifier: License :: OSI Approved :: MIT License
Requires-Python: >=3.8
License-File: LICENSE
